MANIFEST.in
README.rst
buildout.cfg
develop.cfg
requirements.txt
setup.py
version.txt
bob/__init__.py
bob.db.replaymobile.egg-info/PKG-INFO
bob.db.replaymobile.egg-info/SOURCES.txt
bob.db.replaymobile.egg-info/dependency_links.txt
bob.db.replaymobile.egg-info/entry_points.txt
bob.db.replaymobile.egg-info/namespace_packages.txt
bob.db.replaymobile.egg-info/not-zip-safe
bob.db.replaymobile.egg-info/requires.txt
bob.db.replaymobile.egg-info/top_level.txt
bob/db/__init__.py
bob/db/replaymobile/__init__.py
bob/db/replaymobile/checkfiles.py
bob/db/replaymobile/create.py
bob/db/replaymobile/db.sql3
bob/db/replaymobile/driver.py
bob/db/replaymobile/dumplist.py
bob/db/replaymobile/models.py
bob/db/replaymobile/query.py
bob/db/replaymobile/test.py
bob/db/replaymobile/verificationprotocol.py
doc/conf.py
doc/guide.rst
doc/index.rst
doc/py_api.rst