Metadata-Version: 1.1
Name: bob.db.replaymobile
Version: 1.1.4
Summary: Replay-Mobile Database Access API for Bob
Home-page: https://gitlab.idiap.ch/bob/bob.db.replaymobile
Author: Artur Costa-Pazo, Andre Anjos, Ivana Chingovska, Sushil Bhattacharjee
Author-email: andre.anjos@idiap.ch, ivana.chingovska@idiap.ch, sushil.bhattacharjee@idiap.ch
License: BSD
Platform: UNKNOWN
Classifier: Framework :: Bob
Classifier: Development Status :: 4 - Beta
Classifier: Intended Audience :: Science/Research
Classifier: License :: OSI Approved :: BSD License
Classifier: Natural Language :: English
Classifier: Programming Language :: Python
Classifier: Programming Language :: Python :: 3
Classifier: Topic :: Scientific/Engineering :: Artificial Intelligence
Classifier: Topic :: Database :: Front-Ends
